mlc/main.py
mlperf-0.1.0.dist-info/LICENSE
mlperf-0.1.0.dist-info/METADATA
mlperf-0.1.0.dist-info/WHEEL
mlperf-0.1.0.dist-info/top_level.txt
mlperf-0.1.0.dist-info/RECORD
