Metadata-Version: 2.2
Name: mlperf
Version: 0.1.0
Summary: An automation interface for ML applications
Author-email: Arjun <arjun@gateoverflow.com>
License:                                  Apache License
Project-URL: Homepage, https://github.com/gateoverflow/mlc
Project-URL: Documentation, https://gateoverflow.github.io/mlc
Project-URL: Repository, https://github.com/gateoverflow/mlc
Project-URL: Issues, https://github.com/gateoverflow/mlc/issues
Keywords: mlc,pypi,package,automation
Classifier: Programming Language :: Python :: 3
Classifier: License :: OSI Approved :: Apache Software License
Classifier: Operating System :: OS Independent
Requires-Python: >=3.7
License-File: LICENSE
Requires-Dist: requests
